{
	"partitions" : [
		{
			"name" : "Top",
			"pins" : [
				{
					"name" : "tx_done",
					"strict" : false
				},
				{
					"name" : "payload_req_o",
					"strict" : false
				},
				{
					"name" : "gmii_tx_clk",
					"strict" : false
				},
				{
					"name" : "gmii_txen",
					"strict" : false
				},
				{
					"name" : "gmii_txd[0]",
					"strict" : false
				},
				{
					"name" : "gmii_txd[1]",
					"strict" : false
				},
				{
					"name" : "gmii_txd[2]",
					"strict" : false
				},
				{
					"name" : "gmii_txd[3]",
					"strict" : false
				},
				{
					"name" : "gmii_txd[4]",
					"strict" : false
				},
				{
					"name" : "gmii_txd[5]",
					"strict" : false
				},
				{
					"name" : "gmii_txd[6]",
					"strict" : false
				},
				{
					"name" : "gmii_txd[7]",
					"strict" : false
				},
				{
					"name" : "clk_125m",
					"strict" : false
				},
				{
					"name" : "rst_n",
					"strict" : false
				},
				{
					"name" : "data_len[0]",
					"strict" : false
				},
				{
					"name" : "tx_en_pulse",
					"strict" : false
				},
				{
					"name" : "data_len[1]",
					"strict" : false
				},
				{
					"name" : "data_len[2]",
					"strict" : false
				},
				{
					"name" : "data_len[3]",
					"strict" : false
				},
				{
					"name" : "data_len[4]",
					"strict" : false
				},
				{
					"name" : "data_len[5]",
					"strict" : false
				},
				{
					"name" : "data_len[6]",
					"strict" : false
				},
				{
					"name" : "data_len[7]",
					"strict" : false
				},
				{
					"name" : "data_len[8]",
					"strict" : false
				},
				{
					"name" : "data_len[9]",
					"strict" : false
				},
				{
					"name" : "data_len[11]",
					"strict" : false
				},
				{
					"name" : "data_len[10]",
					"strict" : false
				},
				{
					"name" : "data_len[12]",
					"strict" : false
				},
				{
					"name" : "data_len[13]",
					"strict" : false
				},
				{
					"name" : "data_len[14]",
					"strict" : false
				},
				{
					"name" : "data_len[15]",
					"strict" : false
				},
				{
					"name" : "payload_dat_i[0]",
					"strict" : false
				},
				{
					"name" : "payload_dat_i[1]",
					"strict" : false
				},
				{
					"name" : "payload_dat_i[2]",
					"strict" : false
				},
				{
					"name" : "payload_dat_i[3]",
					"strict" : false
				},
				{
					"name" : "payload_dat_i[4]",
					"strict" : false
				},
				{
					"name" : "payload_dat_i[5]",
					"strict" : false
				},
				{
					"name" : "payload_dat_i[6]",
					"strict" : false
				},
				{
					"name" : "payload_dat_i[7]",
					"strict" : false
				},
				{
					"name" : "dst_port[8]",
					"strict" : false
				},
				{
					"name" : "src_port[0]",
					"strict" : false
				},
				{
					"name" : "src_port[8]",
					"strict" : false
				},
				{
					"name" : "dst_port[0]",
					"strict" : false
				},
				{
					"name" : "dst_mac[0]",
					"strict" : false
				},
				{
					"name" : "src_mac[40]",
					"strict" : false
				},
				{
					"name" : "dst_mac[8]",
					"strict" : false
				},
				{
					"name" : "src_mac[32]",
					"strict" : false
				},
				{
					"name" : "dst_mac[24]",
					"strict" : false
				},
				{
					"name" : "dst_mac[32]",
					"strict" : false
				},
				{
					"name" : "dst_mac[40]",
					"strict" : false
				},
				{
					"name" : "dst_mac[16]",
					"strict" : false
				},
				{
					"name" : "src_mac[8]",
					"strict" : false
				},
				{
					"name" : "src_mac[16]",
					"strict" : false
				},
				{
					"name" : "src_mac[24]",
					"strict" : false
				},
				{
					"name" : "src_mac[0]",
					"strict" : false
				},
				{
					"name" : "dst_ip[8]",
					"strict" : false
				},
				{
					"name" : "dst_ip[16]",
					"strict" : false
				},
				{
					"name" : "dst_ip[24]",
					"strict" : false
				},
				{
					"name" : "dst_ip[0]",
					"strict" : false
				},
				{
					"name" : "src_ip[16]",
					"strict" : false
				},
				{
					"name" : "src_ip[24]",
					"strict" : false
				},
				{
					"name" : "src_ip[8]",
					"strict" : false
				},
				{
					"name" : "src_ip[15]",
					"strict" : false
				},
				{
					"name" : "src_ip[14]",
					"strict" : false
				},
				{
					"name" : "src_ip[13]",
					"strict" : false
				},
				{
					"name" : "src_ip[12]",
					"strict" : false
				},
				{
					"name" : "src_ip[11]",
					"strict" : false
				},
				{
					"name" : "src_ip[10]",
					"strict" : false
				},
				{
					"name" : "src_ip[9]",
					"strict" : false
				},
				{
					"name" : "src_ip[7]",
					"strict" : false
				},
				{
					"name" : "src_ip[6]",
					"strict" : false
				},
				{
					"name" : "src_ip[5]",
					"strict" : false
				},
				{
					"name" : "src_ip[4]",
					"strict" : false
				},
				{
					"name" : "src_ip[3]",
					"strict" : false
				},
				{
					"name" : "src_ip[2]",
					"strict" : false
				},
				{
					"name" : "src_ip[1]",
					"strict" : false
				},
				{
					"name" : "src_ip[0]",
					"strict" : false
				},
				{
					"name" : "src_ip[31]",
					"strict" : false
				},
				{
					"name" : "src_ip[30]",
					"strict" : false
				},
				{
					"name" : "src_ip[29]",
					"strict" : false
				},
				{
					"name" : "src_ip[28]",
					"strict" : false
				},
				{
					"name" : "src_ip[27]",
					"strict" : false
				},
				{
					"name" : "src_ip[26]",
					"strict" : false
				},
				{
					"name" : "src_ip[25]",
					"strict" : false
				},
				{
					"name" : "src_ip[23]",
					"strict" : false
				},
				{
					"name" : "src_ip[22]",
					"strict" : false
				},
				{
					"name" : "src_ip[21]",
					"strict" : false
				},
				{
					"name" : "src_ip[20]",
					"strict" : false
				},
				{
					"name" : "src_ip[19]",
					"strict" : false
				},
				{
					"name" : "src_ip[18]",
					"strict" : false
				},
				{
					"name" : "src_ip[17]",
					"strict" : false
				},
				{
					"name" : "dst_ip[31]",
					"strict" : false
				},
				{
					"name" : "dst_ip[30]",
					"strict" : false
				},
				{
					"name" : "dst_ip[29]",
					"strict" : false
				},
				{
					"name" : "dst_ip[28]",
					"strict" : false
				},
				{
					"name" : "dst_ip[27]",
					"strict" : false
				},
				{
					"name" : "dst_ip[26]",
					"strict" : false
				},
				{
					"name" : "dst_ip[25]",
					"strict" : false
				},
				{
					"name" : "dst_ip[23]",
					"strict" : false
				},
				{
					"name" : "dst_ip[22]",
					"strict" : false
				},
				{
					"name" : "dst_ip[21]",
					"strict" : false
				},
				{
					"name" : "dst_ip[20]",
					"strict" : false
				},
				{
					"name" : "dst_ip[19]",
					"strict" : false
				},
				{
					"name" : "dst_ip[18]",
					"strict" : false
				},
				{
					"name" : "dst_ip[17]",
					"strict" : false
				},
				{
					"name" : "dst_ip[15]",
					"strict" : false
				},
				{
					"name" : "dst_ip[14]",
					"strict" : false
				},
				{
					"name" : "dst_ip[13]",
					"strict" : false
				},
				{
					"name" : "dst_ip[12]",
					"strict" : false
				},
				{
					"name" : "dst_ip[11]",
					"strict" : false
				},
				{
					"name" : "dst_ip[10]",
					"strict" : false
				},
				{
					"name" : "dst_ip[9]",
					"strict" : false
				},
				{
					"name" : "dst_ip[7]",
					"strict" : false
				},
				{
					"name" : "dst_ip[6]",
					"strict" : false
				},
				{
					"name" : "dst_ip[5]",
					"strict" : false
				},
				{
					"name" : "dst_ip[4]",
					"strict" : false
				},
				{
					"name" : "dst_ip[3]",
					"strict" : false
				},
				{
					"name" : "dst_ip[2]",
					"strict" : false
				},
				{
					"name" : "dst_ip[1]",
					"strict" : false
				},
				{
					"name" : "src_mac[41]",
					"strict" : false
				},
				{
					"name" : "dst_mac[1]",
					"strict" : false
				},
				{
					"name" : "dst_mac[9]",
					"strict" : false
				},
				{
					"name" : "src_mac[33]",
					"strict" : false
				},
				{
					"name" : "dst_mac[33]",
					"strict" : false
				},
				{
					"name" : "dst_mac[25]",
					"strict" : false
				},
				{
					"name" : "dst_mac[41]",
					"strict" : false
				},
				{
					"name" : "dst_mac[17]",
					"strict" : false
				},
				{
					"name" : "src_mac[17]",
					"strict" : false
				},
				{
					"name" : "src_mac[9]",
					"strict" : false
				},
				{
					"name" : "src_mac[25]",
					"strict" : false
				},
				{
					"name" : "src_mac[1]",
					"strict" : false
				},
				{
					"name" : "src_port[1]",
					"strict" : false
				},
				{
					"name" : "dst_port[9]",
					"strict" : false
				},
				{
					"name" : "src_port[9]",
					"strict" : false
				},
				{
					"name" : "dst_port[1]",
					"strict" : false
				},
				{
					"name" : "dst_mac[26]",
					"strict" : false
				},
				{
					"name" : "dst_mac[34]",
					"strict" : false
				},
				{
					"name" : "dst_mac[42]",
					"strict" : false
				},
				{
					"name" : "dst_mac[18]",
					"strict" : false
				},
				{
					"name" : "src_mac[42]",
					"strict" : false
				},
				{
					"name" : "dst_mac[2]",
					"strict" : false
				},
				{
					"name" : "dst_mac[10]",
					"strict" : false
				},
				{
					"name" : "src_mac[34]",
					"strict" : false
				},
				{
					"name" : "dst_port[10]",
					"strict" : false
				},
				{
					"name" : "src_port[2]",
					"strict" : false
				},
				{
					"name" : "src_port[10]",
					"strict" : false
				},
				{
					"name" : "dst_port[2]",
					"strict" : false
				},
				{
					"name" : "src_mac[18]",
					"strict" : false
				},
				{
					"name" : "src_mac[10]",
					"strict" : false
				},
				{
					"name" : "src_mac[26]",
					"strict" : false
				},
				{
					"name" : "src_mac[2]",
					"strict" : false
				},
				{
					"name" : "dst_mac[27]",
					"strict" : false
				},
				{
					"name" : "dst_mac[35]",
					"strict" : false
				},
				{
					"name" : "dst_mac[43]",
					"strict" : false
				},
				{
					"name" : "dst_mac[19]",
					"strict" : false
				},
				{
					"name" : "dst_mac[3]",
					"strict" : false
				},
				{
					"name" : "src_mac[43]",
					"strict" : false
				},
				{
					"name" : "dst_mac[11]",
					"strict" : false
				},
				{
					"name" : "src_mac[35]",
					"strict" : false
				},
				{
					"name" : "dst_port[11]",
					"strict" : false
				},
				{
					"name" : "src_port[3]",
					"strict" : false
				},
				{
					"name" : "src_port[11]",
					"strict" : false
				},
				{
					"name" : "dst_port[3]",
					"strict" : false
				},
				{
					"name" : "src_mac[11]",
					"strict" : false
				},
				{
					"name" : "src_mac[19]",
					"strict" : false
				},
				{
					"name" : "src_mac[3]",
					"strict" : false
				},
				{
					"name" : "src_mac[27]",
					"strict" : false
				},
				{
					"name" : "dst_mac[36]",
					"strict" : false
				},
				{
					"name" : "dst_mac[28]",
					"strict" : false
				},
				{
					"name" : "dst_mac[44]",
					"strict" : false
				},
				{
					"name" : "dst_mac[20]",
					"strict" : false
				},
				{
					"name" : "src_mac[44]",
					"strict" : false
				},
				{
					"name" : "dst_mac[4]",
					"strict" : false
				},
				{
					"name" : "dst_mac[12]",
					"strict" : false
				},
				{
					"name" : "src_mac[36]",
					"strict" : false
				},
				{
					"name" : "src_port[4]",
					"strict" : false
				},
				{
					"name" : "dst_port[12]",
					"strict" : false
				},
				{
					"name" : "src_port[12]",
					"strict" : false
				},
				{
					"name" : "dst_port[4]",
					"strict" : false
				},
				{
					"name" : "src_mac[20]",
					"strict" : false
				},
				{
					"name" : "src_mac[12]",
					"strict" : false
				},
				{
					"name" : "src_mac[28]",
					"strict" : false
				},
				{
					"name" : "src_mac[4]",
					"strict" : false
				},
				{
					"name" : "dst_mac[29]",
					"strict" : false
				},
				{
					"name" : "dst_mac[37]",
					"strict" : false
				},
				{
					"name" : "dst_mac[45]",
					"strict" : false
				},
				{
					"name" : "dst_mac[21]",
					"strict" : false
				},
				{
					"name" : "dst_mac[5]",
					"strict" : false
				},
				{
					"name" : "src_mac[45]",
					"strict" : false
				},
				{
					"name" : "dst_mac[13]",
					"strict" : false
				},
				{
					"name" : "src_mac[37]",
					"strict" : false
				},
				{
					"name" : "dst_port[13]",
					"strict" : false
				},
				{
					"name" : "src_port[5]",
					"strict" : false
				},
				{
					"name" : "src_port[13]",
					"strict" : false
				},
				{
					"name" : "dst_port[5]",
					"strict" : false
				},
				{
					"name" : "src_mac[13]",
					"strict" : false
				},
				{
					"name" : "src_mac[21]",
					"strict" : false
				},
				{
					"name" : "src_mac[29]",
					"strict" : false
				},
				{
					"name" : "src_mac[5]",
					"strict" : false
				},
				{
					"name" : "dst_mac[38]",
					"strict" : false
				},
				{
					"name" : "dst_mac[30]",
					"strict" : false
				},
				{
					"name" : "dst_mac[46]",
					"strict" : false
				},
				{
					"name" : "dst_mac[22]",
					"strict" : false
				},
				{
					"name" : "src_mac[46]",
					"strict" : false
				},
				{
					"name" : "dst_mac[6]",
					"strict" : false
				},
				{
					"name" : "dst_mac[14]",
					"strict" : false
				},
				{
					"name" : "src_mac[38]",
					"strict" : false
				},
				{
					"name" : "src_port[6]",
					"strict" : false
				},
				{
					"name" : "dst_port[14]",
					"strict" : false
				},
				{
					"name" : "src_port[14]",
					"strict" : false
				},
				{
					"name" : "dst_port[6]",
					"strict" : false
				},
				{
					"name" : "src_mac[22]",
					"strict" : false
				},
				{
					"name" : "src_mac[14]",
					"strict" : false
				},
				{
					"name" : "src_mac[30]",
					"strict" : false
				},
				{
					"name" : "src_mac[6]",
					"strict" : false
				},
				{
					"name" : "dst_port[15]",
					"strict" : false
				},
				{
					"name" : "src_port[7]",
					"strict" : false
				},
				{
					"name" : "src_port[15]",
					"strict" : false
				},
				{
					"name" : "dst_port[7]",
					"strict" : false
				},
				{
					"name" : "dst_mac[7]",
					"strict" : false
				},
				{
					"name" : "src_mac[47]",
					"strict" : false
				},
				{
					"name" : "dst_mac[15]",
					"strict" : false
				},
				{
					"name" : "src_mac[39]",
					"strict" : false
				},
				{
					"name" : "dst_mac[31]",
					"strict" : false
				},
				{
					"name" : "dst_mac[39]",
					"strict" : false
				},
				{
					"name" : "dst_mac[47]",
					"strict" : false
				},
				{
					"name" : "dst_mac[23]",
					"strict" : false
				},
				{
					"name" : "src_mac[15]",
					"strict" : false
				},
				{
					"name" : "src_mac[23]",
					"strict" : false
				},
				{
					"name" : "src_mac[31]",
					"strict" : false
				},
				{
					"name" : "src_mac[7]",
					"strict" : false
				}
			]
		}
	]
}